tranquil/__init__.py
tranquil-0.0.1.dist-info/LICENSE
tranquil-0.0.1.dist-info/METADATA
tranquil-0.0.1.dist-info/WHEEL
tranquil-0.0.1.dist-info/top_level.txt
tranquil-0.0.1.dist-info/RECORD
