Metadata-Version: 2.1
Name: tranquil
Version: 0.0.1
Summary: Twitter Academic API Client.
Home-page: https://github.com/ysenarath/tranquil
Author: Yasas Senarath
License: UNKNOWN
Platform: UNKNOWN
Classifier: Programming Language :: Python :: 3
Classifier: License :: OSI Approved :: MIT License
Classifier: Operating System :: OS Independent
Requires-Python: >=3.6
License-File: LICENSE
